yggdirsil/__init__.py
yggdirsil-0.0.0.dist-info/LICENSE
yggdirsil-0.0.0.dist-info/WHEEL
yggdirsil-0.0.0.dist-info/METADATA
yggdirsil-0.0.0.dist-info/RECORD
