Metadata-Version: 2.1
Name: yggdirsil
Version: 0.0.0
Summary: Your cloud-based files, within reach.
Author: Orlando Ospino Sánchez
Author-email: oroschz@outlook.com
Requires-Python: >=3.7,<4.0
Classifier: Development Status :: 1 - Planning
Classifier: Programming Language :: Python :: 3
Classifier: Programming Language :: Python :: 3.10
Classifier: Programming Language :: Python :: 3.7
Classifier: Programming Language :: Python :: 3.8
Classifier: Programming Language :: Python :: 3.9
